jammies/cli.py
jammies/config.py
jammies/log.py
jammies/module.py
jammies/registrar.py
jammies/utils.py
jammies/defn/builder.py
jammies/defn/file.py
jammies/defn/metadata.py
jammies/defn/registrar.py
jammies/internal/file/gitrepo.py
jammies/internal/file/osf.py
jammies/internal/file/url.py
jammies/internal/file/delegate/gitrepo.py
jammies/internal/postprocessor/fops.py
jammies/internal/postprocessor/notebook.py
jammies/internal/postprocessor/pand.py
jammies/internal/postprocessor/unpack.py
jammies/struct/codec.py
jammies/struct/registry.py
jammies/workspace/patcher.py
jammies/workspace/project.py
jammies-0.5.0.dist-info/LICENSE
jammies-0.5.0.dist-info/METADATA
jammies-0.5.0.dist-info/WHEEL
jammies-0.5.0.dist-info/entry_points.txt
jammies-0.5.0.dist-info/top_level.txt
jammies-0.5.0.dist-info/RECORD
