Metadata-Version: 2.1
Name: jammies
Version: 0.5.0
Summary: A helper for constructing, managing, and patching projects
Author-email: Aaron Haim <ahaim@ashwork.net>
License: MIT License
Project-URL: homepage, https://github.com/ahaim5357/jammies
Project-URL: issue_tracker, https://github.com/ahaim5357/jammies/issues
Requires-Python: >=3.8
License-File: LICENSE
Requires-Dist: requests >=2.28
Requires-Dist: click >=8.1
Requires-Dist: tomlkit >=0.11.8
Requires-Dist: platformdirs >=3.5
Provides-Extra: all
Requires-Dist: jammies[git,notebook] ; extra == 'all'
Provides-Extra: git
Requires-Dist: GitPython >=3.1 ; extra == 'git'
Provides-Extra: notebook
Requires-Dist: nbconvert >=7 ; extra == 'notebook'
Requires-Dist: ipython >=7 ; extra == 'notebook'
